rapids_env_generator/__init__.py
rapids_env_generator/_version.py
rapids_env_generator/cli.py
rapids_env_generator/rapids_env_generator.py
rapids_env_generator-0.0.5.dist-info/LICENSE
rapids_env_generator-0.0.5.dist-info/METADATA
rapids_env_generator-0.0.5.dist-info/WHEEL
rapids_env_generator-0.0.5.dist-info/entry_points.txt
rapids_env_generator-0.0.5.dist-info/top_level.txt
rapids_env_generator-0.0.5.dist-info/RECORD
